cms_lab_publications/__init__.py
cms_lab_publications/admin.py
cms_lab_publications/cms_plugins.py
cms_lab_publications/cms_toolbar.py
cms_lab_publications/models.py
cms_lab_publications/tests.py
cms_lab_publications/views.py
cms_lab_publications/static/cms_lab_publications/app.css
cms_lab_publications/static/cms_lab_publications/css/admin-publication-filter.css
cms_lab_publications/static/cms_lab_publications/js/list.min.js
cms_lab_publications/static/cms_lab_publications/js/list.pagination.min.js
cms_lab_publications/static/cms_lab_publications/js/search-filter-pubs.js
cms_lab_publications/templates/cms_lab_publications/_buttons.html
cms_lab_publications/templates/cms_lab_publications/_header-with-search-filter.html
cms_lab_publications/templates/cms_lab_publications/_modal.html
cms_lab_publications/templates/cms_lab_publications/plugin.html
djangocms_lab_publications-0.1.5.dist-info/DESCRIPTION.rst
djangocms_lab_publications-0.1.5.dist-info/METADATA
djangocms_lab_publications-0.1.5.dist-info/metadata.json
djangocms_lab_publications-0.1.5.dist-info/RECORD
djangocms_lab_publications-0.1.5.dist-info/top_level.txt
djangocms_lab_publications-0.1.5.dist-info/WHEEL
