Metadata-Version: 2.0
Name: djangocms-lab-publications
Version: 0.1.5
Summary: A Django app for adding sets of scientific publications with PubMed metadata to a Django site with django CMS-specific features
Home-page: https://github.com/mfcovington/djangocms-lab-publications
Author: Michael F. Covington
Author-email: mfcovington@gmail.com
License: BSD License
Keywords: citations lab literature pmid publications pubmed science
Platform: UNKNOWN
Classifier: Development Status :: 3 - Alpha
Classifier: Environment :: Web Environment
Classifier: Framework :: Django
Classifier: Framework :: Django :: 1.7
Classifier: Framework :: Django :: 1.8
Classifier: Intended Audience :: Developers
Classifier: Intended Audience :: Science/Research
Classifier: License :: OSI Approved :: BSD License
Classifier: Operating System :: OS Independent
Classifier: Programming Language :: Python
Classifier: Programming Language :: Python :: 3
Classifier: Programming Language :: Python :: 3.2
Classifier: Programming Language :: Python :: 3.3
Classifier: Programming Language :: Python :: 3.4
Classifier: Programming Language :: Python :: 3 :: Only
Classifier: Topic :: Internet :: WWW/HTTP
Classifier: Topic :: Internet :: WWW/HTTP :: Dynamic Content
Requires-Dist: Django (>=1.7)
Requires-Dist: django-cms (>=3.0.7)
Requires-Dist: django-filer (>=0.9.10)
Requires-Dist: django-taggit (>=0.14.0)
Requires-Dist: django-taggit-helpers (>=0.1.1)
Requires-Dist: pubmed-lookup (>=0.1.1)
